MANIFEST.in
setup.py
py2oracle/README.rst
py2oracle/__init__.py
py2oracle/jaydebe2Oracle.py
py2oracle/jaydebe2OracleOO.py
py2oracle.egg-info/PKG-INFO
py2oracle.egg-info/SOURCES.txt
py2oracle.egg-info/dependency_links.txt
py2oracle.egg-info/not-zip-safe
py2oracle.egg-info/requires.txt
py2oracle.egg-info/top_level.txt
py2oracle/jar/ojdbc6.jar