Metadata-Version: 1.1
Name: py2oracle
Version: 0.4
Summary: use py to read Oracle DB
Home-page: http://rkalva89828.kau.roche.com/gpa/py2oracle
Author: Jian Dai
Author-email: daij12@gene.com
License: MIT
Keywords: oracle db query
Platform: UNKNOWN
Classifier: Development Status :: 3 - Alpha
Classifier: License :: OSI Approved :: MIT License
Classifier: Programming Language :: Python :: 2.7
